{
  "slug": "grape-up",
  "name": "Grape Up",
  "status": "applied",
  "stage": "talent_pool",
  "process": "Applied to talent pool for upcoming Senior QA Engineer opportunities",
  "requirements": "Senior QA Engineer; 5+ years QA; Playwright 3+ years; TypeScript; Page Object Pattern; Git; API testing; performance testing; Artillery.io or Grafana k6; GitHub Actions; JIRA/Xray; BDD; large-scale corporate projects; English B2+",
  "notes": "Applied. This is a talent pool posting, meaning there may be no immediate open seat; candidates are collected and contacted when a matching project opens.",
  "links": [
    "https://careers.grapeup.com/career/senior-qa-engineer-3/"
  ],
  "fit": "9/10",
  "recommendedCv": "CV 2",
  "outreach": "Applied via careers page",
  "updatedAt": "2026-04-03T21:24:08.253Z"
}
