{
  "slug": "infogain",
  "name": "Infogain",
  "status": "target",
  "stage": "cv_to_send",
  "process": "Imported from JustJoinIt shortlist",
  "requirements": "Senior QA Automation Engineer; Stack: Playwright, Java, Selenium, REST, API, Performance",
  "notes": "Imported from ranked shortlist CSV. Vacancy: Senior QA Automation Engineer.",
  "links": [
    "https://justjoin.it/job-offer/infogain-senior-qa-automation-engineer-krakow-testing"
  ],
  "fit": "88/100",
  "recommendedCv": "CV 2",
  "outreach": "Shortlisted from CSV",
  "updatedAt": "2026-04-16T10:25:48.335Z"
}
